django_ai_support/__init__.py
django_ai_support/apps.py
django_ai_support/backends.py
django_ai_support/conf.py
django_ai_support/graphs.py
django_ai_support/serializers.py
django_ai_support/settings.py
django_ai_support/views.py
django_ai_support-0.1.8.dist-info/licenses/LICENSE
django_ai_support-0.1.8.dist-info/METADATA
django_ai_support-0.1.8.dist-info/WHEEL
django_ai_support-0.1.8.dist-info/top_level.txt
django_ai_support-0.1.8.dist-info/RECORD
