Metadata-Version: 2.4
Name: django-ai-support
Version: 0.1.8
Summary: AI support for your django app.
Author-email: EmadDeve20 <emaddeve20@gmail.com>
License-Expression: GPL-3.0-or-later
Project-URL: Homepage, https://github.com/EmadDeve20/django-ai-support
Project-URL: Issues, https://github.com/EmadDeve20/django-ai-support/issues
Classifier: Environment :: Web Environment
Classifier: Framework :: Django
Classifier: Framework :: Django :: 4.0
Classifier: Intended Audience :: Developers
Classifier: Operating System :: OS Independent
Classifier: Programming Language :: Python
Classifier: Programming Language :: Python :: 3
Classifier: Programming Language :: Python :: 3 :: Only
Classifier: Programming Language :: Python :: 3.10
Classifier: Programming Language :: Python :: 3.11
Classifier: Programming Language :: Python :: 3.12
Classifier: Programming Language :: Python :: 3.13
Classifier: Programming Language :: Python :: 3.14
Classifier: Topic :: Internet :: WWW/HTTP
Classifier: Topic :: Internet :: WWW/HTTP :: Dynamic Content
Requires-Python: >=3.10
License-File: LICENSE
Requires-Dist: Django>=4.0
Requires-Dist: djangorestframework>=3.13.1
Requires-Dist: langchain>=0.3.27
Requires-Dist: langchain>=0.3.27
Requires-Dist: langgraph>=0.6.10
Requires-Dist: drf-spectacular>=0.24.2
Dynamic: license-file
